fastapi_plugin/__init__.py
fastapi_plugin/fast_api_client.py
fastapi_plugin/test_utils.py
fastapi_plugin/utils.py
auth0_fastapi_api-1.0.0b4.dist-info/METADATA
auth0_fastapi_api-1.0.0b4.dist-info/WHEEL
auth0_fastapi_api-1.0.0b4.dist-info/licenses/LICENSE
auth0_fastapi_api-1.0.0b4.dist-info/RECORD
