Metadata-Version: 2.4
Name: auth0-fastapi-api
Version: 1.0.0b4
Summary: SDK for verifying access tokens and securing APIs with Auth0, using Authlib.
License: MIT
License-File: LICENSE
Author: Auth0
Author-email: support@okta.com
Requires-Python: >=3.9,<4.0
Classifier: License :: OSI Approved :: MIT License
Classifier: Programming Language :: Python :: 3
Classifier: Programming Language :: Python :: 3.9
Classifier: Programming Language :: Python :: 3.10
Classifier: Programming Language :: Python :: 3.11
Classifier: Programming Language :: Python :: 3.12
Classifier: Programming Language :: Python :: 3.13
Classifier: Programming Language :: Python :: 3.14
Requires-Dist: auth0-api-python (>=1.0.0b5)
Requires-Dist: fastapi (>=0.115.11,<0.116.0)
Requires-Dist: httpx (>=0.28.1,<0.29.0)
Requires-Dist: uvicorn (>=0.34.0,<0.35.0)
